setup.py
boludistributions/Binomialdistribution.py
boludistributions/Gaussiandistribution.py
boludistributions/Generaldistribution.py
boludistributions/__init__.py
boludistributions.egg-info/PKG-INFO
boludistributions.egg-info/SOURCES.txt
boludistributions.egg-info/dependency_links.txt
boludistributions.egg-info/not-zip-safe
boludistributions.egg-info/top_level.txt